[{"bbox": [98, 0, 144, 46], "category_id": 37, "category_name": "notifications"}, {"bbox": [178, 41, 211, 74], "category_id": 96, "category_name": "call"}, {"bbox": [53, 95, 71, 113], "category_id": 45, "category_name": "thumbs_up"}, {"bbox": [771, 142, 817, 188], "category_id": 42, "category_name": "clock"}, {"bbox": [574, 256, 623, 305], "category_id": 77, "category_name": "dashboard"}, {"bbox": [739, 32, 786, 79], "category_id": 33, "category_name": "camera"}, {"bbox": [147, 156, 180, 182], "category_id": 71, "category_name": "qr_code"}, {"bbox": [258, 21, 276, 35], "category_id": 97, "category_name": "video_camera"}, {"bbox": [934, 88, 955, 109], "category_id": 31, "category_name": "pinterest"}, {"bbox": [241, 316, 256, 330], "category_id": 97, "category_name": "video_camera"}, {"bbox": [873, 279, 889, 290], "category_id": 73, "category_name": "profile_avatar"}, {"bbox": [186, 100, 208, 131], "category_id": 28, "category_name": "airplane"}, {"bbox": [24, 221, 54, 251], "category_id": 66, "category_name": "save"}, {"bbox": [236, 285, 259, 306], "category_id": 36, "category_name": "arrow_up"}, {"bbox": [302, 310, 317, 325], "category_id": 2, "category_name": "car"}, {"bbox": [468, 187, 497, 213], "category_id": 20, "category_name": "headphones"}, {"bbox": [165, 216, 193, 255], "category_id": 58, "category_name": "contrast"}, {"bbox": [166, 344, 182, 360], "category_id": 44, "category_name": "map"}, {"bbox": [200, 341, 210, 351], "category_id": 62, "category_name": "arrow_left"}, {"bbox": [935, 294, 968, 344], "category_id": 67, "category_name": "play"}, {"bbox": [431, 108, 466, 149], "category_id": 16, "category_name": "music"}, {"bbox": [381, 28, 409, 56], "category_id": 102, "category_name": "globe"}, {"bbox": [124, 333, 154, 363], "category_id": 24, "category_name": "printer"}, {"bbox": [123, 47, 168, 94], "category_id": 21, "category_name": "alarm"}, {"bbox": [436, 355, 483, 405], "category_id": 14, "category_name": "mail"}, {"bbox": [539, 360, 569, 395], "category_id": 6, "category_name": "gift"}, {"bbox": [917, 243, 934, 253], "category_id": 80, "category_name": "close"}, {"bbox": [522, 174, 537, 189], "category_id": 60, "category_name": "minimize"}, {"bbox": [197, 301, 227, 336], "category_id": 29, "category_name": "cursor"}, {"bbox": [1, 247, 23, 269], "category_id": 64, "category_name": "tag"}, {"bbox": [666, 170, 716, 220], "category_id": 5, "category_name": "ticket"}, {"bbox": [499, 31, 549, 81], "category_id": 9, "category_name": "send"}, {"bbox": [385, 295, 435, 343], "category_id": 103, "category_name": "arrow_right"}, {"bbox": [49, 38, 76, 72], "category_id": 1, "category_name": "filter"}, {"bbox": [378, 112, 418, 162], "category_id": 12, "category_name": "trash"}, {"bbox": [511, 118, 521, 128], "category_id": 12, "category_name": "trash"}, {"bbox": [73, 348, 95, 370], "category_id": 40, "category_name": "inbox"}, {"bbox": [521, 271, 560, 310], "category_id": 85, "category_name": "share"}, {"bbox": [603, 175, 615, 187], "category_id": 77, "category_name": "dashboard"}, {"bbox": [682, 361, 694, 378], "category_id": 48, "category_name": "flashlight"}, {"bbox": [484, 136, 522, 168], "category_id": 84, "category_name": "fab"}, {"bbox": [602, 342, 640, 380], "category_id": 103, "category_name": "arrow_right"}, {"bbox": [573, 20, 610, 45], "category_id": 66, "category_name": "save"}, {"bbox": [836, 24, 847, 35], "category_id": 85, "category_name": "share"}, {"bbox": [549, 84, 597, 132], "category_id": 68, "category_name": "file"}, {"bbox": [333, 255, 365, 287], "category_id": 64, "category_name": "tag"}, {"bbox": [129, 202, 153, 226], "category_id": 4, "category_name": "eye"}, {"bbox": [113, 228, 142, 257], "category_id": 7, "category_name": "delete"}, {"bbox": [117, 364, 150, 397], "category_id": 72, "category_name": "add"}, {"bbox": [270, 154, 310, 195], "category_id": 11, "category_name": "arrow_down"}, {"bbox": [607, 76, 627, 96], "category_id": 20, "category_name": "headphones"}, {"bbox": [322, 350, 350, 378], "category_id": 16, "category_name": "music"}, {"bbox": [276, 325, 321, 368], "category_id": 100, "category_name": "signal"}, {"bbox": [454, 36, 484, 82], "category_id": 40, "category_name": "inbox"}, {"bbox": [939, 208, 960, 229], "category_id": 87, "category_name": "settings"}, {"bbox": [206, 224, 234, 255], "category_id": 63, "category_name": "volume"}, {"bbox": [798, 244, 829, 275], "category_id": 84, "category_name": "fab"}, {"bbox": [367, 252, 396, 276], "category_id": 91, "category_name": "external_link"}, {"bbox": [628, 15, 654, 35], "category_id": 87, "category_name": "settings"}, {"bbox": [365, 348, 380, 369], "category_id": 102, "category_name": "globe"}, {"bbox": [84, 190, 118, 224], "category_id": 19, "category_name": "favorite"}, {"bbox": [835, 162, 862, 189], "category_id": 96, "category_name": "call"}, {"bbox": [28, 298, 64, 321], "category_id": 78, "category_name": "television"}, {"bbox": [643, 94, 658, 111], "category_id": 92, "category_name": "moon"}, {"bbox": [432, 185, 457, 216], "category_id": 36, "category_name": "arrow_up"}, {"bbox": [304, 263, 324, 283], "category_id": 99, "category_name": "trophy"}, {"bbox": [870, 239, 901, 272], "category_id": 25, "category_name": "dollar"}, {"bbox": [35, 176, 66, 213], "category_id": 14, "category_name": "mail"}, {"bbox": [321, 19, 334, 29], "category_id": 80, "category_name": "close"}, {"bbox": [814, 45, 850, 81], "category_id": 20, "category_name": "headphones"}, {"bbox": [859, 22, 904, 67], "category_id": 30, "category_name": "sort"}, {"bbox": [332, 54, 381, 103], "category_id": 41, "category_name": "check_mark"}, {"bbox": [319, 156, 367, 204], "category_id": 47, "category_name": "download"}, {"bbox": [445, 300, 485, 342], "category_id": 7, "category_name": "delete"}, {"bbox": [5, 380, 28, 403], "category_id": 83, "category_name": "brightness"}, {"bbox": [833, 367, 851, 385], "category_id": 97, "category_name": "video_camera"}, {"bbox": [684, 115, 731, 162], "category_id": 19, "category_name": "favorite"}, {"bbox": [123, 259, 156, 289], "category_id": 80, "category_name": "close"}, {"bbox": [287, 81, 328, 122], "category_id": 103, "category_name": "arrow_right"}, {"bbox": [405, 175, 430, 200], "category_id": 23, "category_name": "edit"}, {"bbox": [943, 123, 959, 144], "category_id": 2, "category_name": "car"}, {"bbox": [780, 297, 805, 328], "category_id": 1, "category_name": "filter"}, {"bbox": [792, 337, 820, 370], "category_id": 0, "category_name": "calculator"}, {"bbox": [867, 129, 889, 158], "category_id": 19, "category_name": "favorite"}, {"bbox": [414, 248, 453, 287], "category_id": 90, "category_name": "credit_card"}, {"bbox": [543, 257, 555, 267], "category_id": 19, "category_name": "favorite"}, {"bbox": [569, 349, 599, 384], "category_id": 64, "category_name": "tag"}, {"bbox": [892, 91, 921, 120], "category_id": 104, "category_name": "attach"}, {"bbox": [35, 252, 82, 287], "category_id": 58, "category_name": "contrast"}, {"bbox": [236, 240, 272, 276], "category_id": 23, "category_name": "edit"}, {"bbox": [718, 179, 758, 215], "category_id": 13, "category_name": "lock"}, {"bbox": [919, 388, 931, 400], "category_id": 20, "category_name": "headphones"}, {"bbox": [221, 84, 242, 105], "category_id": 71, "category_name": "qr_code"}, {"bbox": [318, 293, 334, 305], "category_id": 42, "category_name": "clock"}, {"bbox": [750, 83, 798, 131], "category_id": 73, "category_name": "profile_avatar"}, {"bbox": [715, 365, 750, 400], "category_id": 102, "category_name": "globe"}, {"bbox": [75, 116, 109, 150], "category_id": 75, "category_name": "location"}, {"bbox": [822, 117, 862, 156], "category_id": 65, "category_name": "facebook"}, {"bbox": [656, 120, 676, 139], "category_id": 86, "category_name": "folder"}, {"bbox": [216, 165, 260, 208], "category_id": 30, "category_name": "sort"}, {"bbox": [559, 169, 574, 184], "category_id": 33, "category_name": "camera"}, {"bbox": [806, 190, 818, 202], "category_id": 8, "category_name": "home"}, {"bbox": [28, 389, 44, 403], "category_id": 6, "category_name": "gift"}, {"bbox": [759, 15, 777, 31], "category_id": 47, "category_name": "download"}, {"bbox": [85, 95, 96, 105], "category_id": 52, "category_name": "crop"}, {"bbox": [547, 224, 567, 248], "category_id": 83, "category_name": "brightness"}, {"bbox": [111, 99, 145, 133], "category_id": 58, "category_name": "contrast"}, {"bbox": [697, 24, 730, 57], "category_id": 10, "category_name": "mute"}, {"bbox": [826, 302, 855, 331], "category_id": 77, "category_name": "dashboard"}, {"bbox": [821, 192, 862, 233], "category_id": 102, "category_name": "globe"}, {"bbox": [640, 314, 681, 355], "category_id": 12, "category_name": "trash"}, {"bbox": [698, 387, 710, 399], "category_id": 64, "category_name": "tag"}, {"bbox": [314, 240, 326, 252], "category_id": 52, "category_name": "crop"}, {"bbox": [744, 290, 762, 312], "category_id": 5, "category_name": "ticket"}, {"bbox": [567, 207, 595, 235], "category_id": 96, "category_name": "call"}, {"bbox": [888, 299, 932, 343], "category_id": 58, "category_name": "contrast"}, {"bbox": [511, 366, 539, 394], "category_id": 34, "category_name": "barcode"}, {"bbox": [87, 54, 98, 67], "category_id": 71, "category_name": "qr_code"}, {"bbox": [917, 145, 961, 189], "category_id": 47, "category_name": "download"}, {"bbox": [820, 282, 833, 293], "category_id": 59, "category_name": "megaphone"}, {"bbox": [453, 260, 484, 291], "category_id": 13, "category_name": "lock"}, {"bbox": [186, 194, 213, 212], "category_id": 2, "category_name": "car"}, {"bbox": [206, 365, 229, 392], "category_id": 15, "category_name": "laptop"}, {"bbox": [337, 219, 358, 240], "category_id": 100, "category_name": "signal"}, {"bbox": [262, 50, 274, 65], "category_id": 78, "category_name": "television"}, {"bbox": [25, 113, 66, 160], "category_id": 28, "category_name": "airplane"}, {"bbox": [616, 141, 638, 159], "category_id": 60, "category_name": "minimize"}, {"bbox": [620, 174, 666, 218], "category_id": 24, "category_name": "printer"}, {"bbox": [4, 67, 18, 85], "category_id": 86, "category_name": "folder"}, {"bbox": [902, 205, 922, 243], "category_id": 1, "category_name": "filter"}, {"bbox": [771, 356, 791, 376], "category_id": 52, "category_name": "crop"}, {"bbox": [715, 226, 738, 249], "category_id": 37, "category_name": "notifications"}, {"bbox": [242, 354, 255, 366], "category_id": 91, "category_name": "external_link"}, {"bbox": [275, 225, 309, 259], "category_id": 72, "category_name": "add"}, {"bbox": [844, 332, 877, 365], "category_id": 60, "category_name": "minimize"}, {"bbox": [887, 365, 913, 403], "category_id": 39, "category_name": "gmail"}, {"bbox": [527, 324, 563, 360], "category_id": 67, "category_name": "play"}, {"bbox": [43, 329, 58, 344], "category_id": 77, "category_name": "dashboard"}, {"bbox": [466, 97, 476, 109], "category_id": 30, "category_name": "sort"}, {"bbox": [751, 216, 785, 250], "category_id": 103, "category_name": "arrow_right"}, {"bbox": [68, 294, 107, 342], "category_id": 92, "category_name": "moon"}, {"bbox": [281, 9, 316, 44], "category_id": 55, "category_name": "chart"}, {"bbox": [698, 268, 710, 280], "category_id": 59, "category_name": "megaphone"}, {"bbox": [492, 92, 506, 104], "category_id": 72, "category_name": "add"}, {"bbox": [601, 106, 619, 129], "category_id": 4, "category_name": "eye"}, {"bbox": [158, 301, 186, 327], "category_id": 66, "category_name": "save"}, {"bbox": [420, 38, 439, 55], "category_id": 86, "category_name": "folder"}, {"bbox": [907, 45, 949, 87], "category_id": 68, "category_name": "file"}, {"bbox": [648, 253, 698, 297], "category_id": 11, "category_name": "arrow_down"}, {"bbox": [825, 1, 841, 17], "category_id": 51, "category_name": "menu"}, {"bbox": [91, 264, 110, 283], "category_id": 57, "category_name": "link"}, {"bbox": [261, 332, 271, 344], "category_id": 104, "category_name": "attach"}, {"bbox": [491, 273, 515, 297], "category_id": 51, "category_name": "menu"}, {"bbox": [34, 287, 45, 297], "category_id": 31, "category_name": "pinterest"}, {"bbox": [335, 103, 376, 144], "category_id": 100, "category_name": "signal"}, {"bbox": [937, 7, 969, 39], "category_id": 14, "category_name": "mail"}, {"bbox": [738, 317, 770, 357], "category_id": 71, "category_name": "qr_code"}, {"bbox": [689, 63, 739, 110], "category_id": 18, "category_name": "grid"}, {"bbox": [196, 6, 220, 30], "category_id": 58, "category_name": "contrast"}, {"bbox": [379, 214, 405, 240], "category_id": 91, "category_name": "external_link"}, {"bbox": [2, 8, 43, 49], "category_id": 56, "category_name": "microphone"}, {"bbox": [21, 174, 35, 188], "category_id": 104, "category_name": "attach"}, {"bbox": [823, 81, 862, 117], "category_id": 56, "category_name": "microphone"}, {"bbox": [390, 69, 429, 101], "category_id": 38, "category_name": "light_bulb"}, {"bbox": [12, 323, 42, 353], "category_id": 99, "category_name": "trophy"}, {"bbox": [736, 254, 764, 273], "category_id": 41, "category_name": "check_mark"}, {"bbox": [243, 83, 283, 123], "category_id": 54, "category_name": "calendar"}, {"bbox": [685, 301, 730, 346], "category_id": 36, "category_name": "arrow_up"}, {"bbox": [106, 357, 117, 367], "category_id": 87, "category_name": "settings"}, {"bbox": [304, 379, 337, 405], "category_id": 30, "category_name": "sort"}, {"bbox": [491, 229, 523, 261], "category_id": 52, "category_name": "crop"}, {"bbox": [810, 22, 831, 43], "category_id": 58, "category_name": "contrast"}, {"bbox": [631, 56, 661, 87], "category_id": 98, "category_name": "user"}, {"bbox": [277, 272, 302, 313], "category_id": 48, "category_name": "flashlight"}, {"bbox": [582, 308, 599, 338], "category_id": 46, "category_name": "battery"}, {"bbox": [829, 336, 841, 346], "category_id": 8, "category_name": "home"}, {"bbox": [399, 363, 432, 396], "category_id": 22, "category_name": "computer"}, {"bbox": [776, 346, 786, 356], "category_id": 96, "category_name": "call"}, {"bbox": [247, 366, 269, 385], "category_id": 5, "category_name": "ticket"}, {"bbox": [666, 34, 691, 59], "category_id": 9, "category_name": "send"}, {"bbox": [145, 95, 185, 129], "category_id": 30, "category_name": "sort"}, {"bbox": [905, 284, 917, 296], "category_id": 100, "category_name": "signal"}, {"bbox": [485, 320, 501, 340], "category_id": 30, "category_name": "sort"}, {"bbox": [863, 160, 880, 180], "category_id": 10, "category_name": "mute"}, {"bbox": [63, 374, 93, 404], "category_id": 60, "category_name": "minimize"}, {"bbox": [613, 23, 625, 33], "category_id": 97, "category_name": "video_camera"}, {"bbox": [654, 222, 681, 249], "category_id": 26, "category_name": "fingerprint"}, {"bbox": [231, 43, 259, 69], "category_id": 30, "category_name": "sort"}, {"bbox": [605, 231, 615, 241], "category_id": 89, "category_name": "cloud"}, {"bbox": [101, 157, 144, 185], "category_id": 73, "category_name": "profile_avatar"}, {"bbox": [344, 313, 378, 333], "category_id": 54, "category_name": "calendar"}, {"bbox": [649, 152, 666, 169], "category_id": 52, "category_name": "crop"}]