[{"bbox": [730, 124, 767, 161], "category_id": 30, "category_name": "sort"}, {"bbox": [734, 355, 767, 379], "category_id": 55, "category_name": "chart"}, {"bbox": [1097, 302, 1144, 349], "category_id": 28, "category_name": "airplane"}, {"bbox": [632, 304, 660, 321], "category_id": 80, "category_name": "close"}, {"bbox": [1144, 146, 1182, 188], "category_id": 40, "category_name": "inbox"}, {"bbox": [1059, 285, 1085, 311], "category_id": 79, "category_name": "refresh"}, {"bbox": [323, 19, 356, 58], "category_id": 48, "category_name": "flashlight"}, {"bbox": [497, 300, 541, 344], "category_id": 45, "category_name": "thumbs_up"}, {"bbox": [30, 172, 51, 193], "category_id": 20, "category_name": "headphones"}, {"bbox": [314, 300, 334, 320], "category_id": 86, "category_name": "folder"}, {"bbox": [1141, 74, 1171, 107], "category_id": 83, "category_name": "brightness"}, {"bbox": [773, 319, 822, 368], "category_id": 23, "category_name": "edit"}, {"bbox": [66, 257, 84, 275], "category_id": 20, "category_name": "headphones"}, {"bbox": [1038, 238, 1082, 274], "category_id": 14, "category_name": "mail"}, {"bbox": [185, 57, 209, 81], "category_id": 6, "category_name": "gift"}, {"bbox": [826, 40, 849, 60], "category_id": 65, "category_name": "facebook"}, {"bbox": [700, 307, 722, 333], "category_id": 32, "category_name": "fast_forward"}, {"bbox": [650, 12, 661, 25], "category_id": 18, "category_name": "grid"}, {"bbox": [236, 44, 251, 59], "category_id": 60, "category_name": "minimize"}, {"bbox": [92, 371, 119, 398], "category_id": 17, "category_name": "bluetooth"}, {"bbox": [638, 167, 672, 201], "category_id": 62, "category_name": "arrow_left"}, {"bbox": [120, 82, 149, 111], "category_id": 101, "category_name": "upload"}, {"bbox": [432, 288, 467, 326], "category_id": 13, "category_name": "lock"}, {"bbox": [144, 36, 165, 53], "category_id": 4, "category_name": "eye"}, {"bbox": [979, 311, 1001, 333], "category_id": 21, "category_name": "alarm"}, {"bbox": [893, 269, 923, 294], "category_id": 87, "category_name": "settings"}, {"bbox": [576, 373, 608, 405], "category_id": 86, "category_name": "folder"}, {"bbox": [1, 29, 47, 75], "category_id": 50, "category_name": "mobile"}, {"bbox": [719, 345, 731, 356], "category_id": 48, "category_name": "flashlight"}, {"bbox": [849, 258, 870, 279], "category_id": 2, "category_name": "car"}, {"bbox": [447, 361, 494, 400], "category_id": 62, "category_name": "arrow_left"}, {"bbox": [248, 330, 276, 363], "category_id": 8, "category_name": "home"}, {"bbox": [194, 383, 231, 420], "category_id": 36, "category_name": "arrow_up"}, {"bbox": [259, 13, 291, 35], "category_id": 92, "category_name": "moon"}, {"bbox": [112, 350, 130, 371], "category_id": 62, "category_name": "arrow_left"}, {"bbox": [349, 108, 384, 143], "category_id": 99, "category_name": "trophy"}, {"bbox": [562, 12, 574, 22], "category_id": 19, "category_name": "favorite"}, {"bbox": [964, 11, 988, 35], "category_id": 36, "category_name": "arrow_up"}, {"bbox": [118, 25, 142, 51], "category_id": 61, "category_name": "overflow_menu"}, {"bbox": [578, 266, 605, 293], "category_id": 67, "category_name": "play"}, {"bbox": [247, 363, 264, 385], "category_id": 101, "category_name": "upload"}, {"bbox": [200, 318, 231, 340], "category_id": 96, "category_name": "call"}, {"bbox": [599, 201, 613, 216], "category_id": 97, "category_name": "video_camera"}, {"bbox": [907, 329, 921, 340], "category_id": 88, "category_name": "fire"}, {"bbox": [609, 8, 629, 30], "category_id": 23, "category_name": "edit"}, {"bbox": [860, 377, 881, 398], "category_id": 77, "category_name": "dashboard"}, {"bbox": [130, 344, 175, 389], "category_id": 57, "category_name": "link"}, {"bbox": [645, 366, 678, 410], "category_id": 46, "category_name": "battery"}, {"bbox": [502, 217, 526, 241], "category_id": 46, "category_name": "battery"}, {"bbox": [554, 119, 596, 161], "category_id": 25, "category_name": "dollar"}, {"bbox": [603, 124, 632, 152], "category_id": 44, "category_name": "map"}, {"bbox": [654, 129, 701, 158], "category_id": 80, "category_name": "close"}, {"bbox": [863, 71, 892, 100], "category_id": 91, "category_name": "external_link"}, {"bbox": [980, 131, 1001, 152], "category_id": 99, "category_name": "trophy"}, {"bbox": [1102, 36, 1151, 66], "category_id": 80, "category_name": "close"}, {"bbox": [417, 147, 447, 191], "category_id": 85, "category_name": "share"}, {"bbox": [816, 16, 843, 39], "category_id": 31, "category_name": "pinterest"}, {"bbox": [37, 326, 75, 364], "category_id": 65, "category_name": "facebook"}, {"bbox": [463, 178, 483, 198], "category_id": 95, "category_name": "twitter"}, {"bbox": [484, 232, 496, 244], "category_id": 76, "category_name": "warning"}, {"bbox": [266, 269, 291, 296], "category_id": 100, "category_name": "signal"}, {"bbox": [369, 189, 414, 238], "category_id": 12, "category_name": "trash"}, {"bbox": [204, 110, 233, 139], "category_id": 72, "category_name": "add"}, {"bbox": [790, 179, 831, 226], "category_id": 4, "category_name": "eye"}, {"bbox": [936, 162, 980, 212], "category_id": 50, "category_name": "mobile"}, {"bbox": [1151, 254, 1181, 284], "category_id": 6, "category_name": "gift"}, {"bbox": [1051, 192, 1093, 235], "category_id": 37, "category_name": "notifications"}, {"bbox": [1127, 123, 1143, 139], "category_id": 73, "category_name": "profile_avatar"}, {"bbox": [327, 375, 341, 392], "category_id": 53, "category_name": "flag"}, {"bbox": [671, 14, 687, 35], "category_id": 50, "category_name": "mobile"}, {"bbox": [149, 271, 159, 281], "category_id": 41, "category_name": "check_mark"}, {"bbox": [863, 159, 895, 179], "category_id": 2, "category_name": "car"}, {"bbox": [500, 121, 538, 159], "category_id": 56, "category_name": "microphone"}, {"bbox": [141, 239, 161, 262], "category_id": 31, "category_name": "pinterest"}, {"bbox": [349, 313, 389, 353], "category_id": 101, "category_name": "upload"}, {"bbox": [546, 200, 586, 240], "category_id": 9, "category_name": "send"}, {"bbox": [492, 175, 521, 200], "category_id": 86, "category_name": "folder"}, {"bbox": [508, 352, 543, 387], "category_id": 15, "category_name": "laptop"}, {"bbox": [39, 84, 82, 127], "category_id": 66, "category_name": "save"}, {"bbox": [1065, 73, 1115, 123], "category_id": 57, "category_name": "link"}, {"bbox": [461, 156, 489, 175], "category_id": 16, "category_name": "music"}, {"bbox": [1094, 172, 1139, 214], "category_id": 11, "category_name": "arrow_down"}, {"bbox": [52, 32, 81, 68], "category_id": 66, "category_name": "save"}, {"bbox": [558, 368, 570, 378], "category_id": 103, "category_name": "arrow_right"}, {"bbox": [442, 98, 485, 141], "category_id": 79, "category_name": "refresh"}, {"bbox": [543, 311, 571, 339], "category_id": 81, "category_name": "maximize"}, {"bbox": [960, 383, 980, 403], "category_id": 48, "category_name": "flashlight"}, {"bbox": [274, 48, 323, 97], "category_id": 39, "category_name": "gmail"}, {"bbox": [6, 283, 21, 296], "category_id": 72, "category_name": "add"}, {"bbox": [202, 160, 227, 178], "category_id": 101, "category_name": "upload"}, {"bbox": [590, 321, 635, 366], "category_id": 10, "category_name": "mute"}, {"bbox": [641, 132, 652, 148], "category_id": 78, "category_name": "television"}, {"bbox": [1111, 146, 1137, 172], "category_id": 46, "category_name": "battery"}, {"bbox": [824, 112, 861, 149], "category_id": 84, "category_name": "fab"}, {"bbox": [97, 181, 119, 199], "category_id": 7, "category_name": "delete"}, {"bbox": [732, 69, 781, 118], "category_id": 36, "category_name": "arrow_up"}, {"bbox": [313, 240, 337, 263], "category_id": 62, "category_name": "arrow_left"}, {"bbox": [466, 199, 487, 228], "category_id": 63, "category_name": "volume"}, {"bbox": [723, 274, 762, 313], "category_id": 39, "category_name": "gmail"}, {"bbox": [1072, 360, 1116, 410], "category_id": 21, "category_name": "alarm"}, {"bbox": [280, 211, 302, 237], "category_id": 94, "category_name": "reply"}, {"bbox": [120, 116, 156, 152], "category_id": 48, "category_name": "flashlight"}, {"bbox": [886, 103, 897, 114], "category_id": 15, "category_name": "laptop"}, {"bbox": [278, 380, 314, 416], "category_id": 22, "category_name": "computer"}, {"bbox": [921, 90, 960, 136], "category_id": 69, "category_name": "google"}, {"bbox": [718, 165, 744, 191], "category_id": 99, "category_name": "trophy"}, {"bbox": [1009, 77, 1057, 125], "category_id": 41, "category_name": "check_mark"}, {"bbox": [414, 37, 455, 63], "category_id": 85, "category_name": "share"}, {"bbox": [1002, 312, 1038, 346], "category_id": 84, "category_name": "fab"}, {"bbox": [357, 23, 403, 69], "category_id": 20, "category_name": "headphones"}, {"bbox": [918, 219, 968, 257], "category_id": 38, "category_name": "light_bulb"}, {"bbox": [995, 220, 1007, 232], "category_id": 36, "category_name": "arrow_up"}, {"bbox": [693, 14, 729, 49], "category_id": 75, "category_name": "location"}, {"bbox": [1139, 205, 1172, 231], "category_id": 95, "category_name": "twitter"}, {"bbox": [63, 219, 73, 229], "category_id": 31, "category_name": "pinterest"}, {"bbox": [648, 82, 671, 111], "category_id": 96, "category_name": "call"}, {"bbox": [115, 215, 133, 240], "category_id": 6, "category_name": "gift"}, {"bbox": [957, 39, 1003, 84], "category_id": 59, "category_name": "megaphone"}, {"bbox": [868, 205, 904, 243], "category_id": 58, "category_name": "contrast"}, {"bbox": [170, 207, 218, 255], "category_id": 28, "category_name": "airplane"}, {"bbox": [897, 176, 911, 187], "category_id": 58, "category_name": "contrast"}, {"bbox": [343, 245, 377, 279], "category_id": 6, "category_name": "gift"}, {"bbox": [113, 296, 159, 342], "category_id": 7, "category_name": "delete"}, {"bbox": [459, 228, 469, 238], "category_id": 101, "category_name": "upload"}, {"bbox": [747, 230, 790, 273], "category_id": 5, "category_name": "ticket"}, {"bbox": [922, 357, 943, 376], "category_id": 44, "category_name": "map"}, {"bbox": [504, 35, 548, 79], "category_id": 34, "category_name": "barcode"}, {"bbox": [887, 17, 935, 65], "category_id": 48, "category_name": "flashlight"}, {"bbox": [687, 242, 720, 275], "category_id": 83, "category_name": "brightness"}, {"bbox": [617, 260, 656, 299], "category_id": 75, "category_name": "location"}, {"bbox": [837, 309, 866, 338], "category_id": 34, "category_name": "barcode"}, {"bbox": [612, 32, 655, 75], "category_id": 65, "category_name": "facebook"}, {"bbox": [489, 257, 521, 289], "category_id": 48, "category_name": "flashlight"}, {"bbox": [620, 160, 638, 188], "category_id": 102, "category_name": "globe"}, {"bbox": [1044, 333, 1067, 347], "category_id": 86, "category_name": "folder"}, {"bbox": [47, 364, 75, 397], "category_id": 98, "category_name": "user"}, {"bbox": [1015, 126, 1062, 173], "category_id": 38, "category_name": "light_bulb"}, {"bbox": [15, 242, 43, 270], "category_id": 1, "category_name": "filter"}, {"bbox": [1151, 321, 1184, 361], "category_id": 86, "category_name": "folder"}, {"bbox": [390, 367, 400, 377], "category_id": 78, "category_name": "television"}, {"bbox": [370, 164, 396, 187], "category_id": 103, "category_name": "arrow_right"}, {"bbox": [1038, 19, 1054, 35], "category_id": 21, "category_name": "alarm"}, {"bbox": [933, 291, 964, 322], "category_id": 10, "category_name": "mute"}, {"bbox": [550, 33, 588, 71], "category_id": 42, "category_name": "clock"}, {"bbox": [1157, 379, 1172, 402], "category_id": 29, "category_name": "cursor"}, {"bbox": [1009, 378, 1036, 409], "category_id": 66, "category_name": "save"}, {"bbox": [29, 212, 44, 229], "category_id": 44, "category_name": "map"}, {"bbox": [231, 303, 257, 329], "category_id": 6, "category_name": "gift"}, {"bbox": [228, 170, 267, 209], "category_id": 57, "category_name": "link"}, {"bbox": [235, 258, 250, 268], "category_id": 69, "category_name": "google"}, {"bbox": [1158, 55, 1173, 70], "category_id": 78, "category_name": "television"}, {"bbox": [141, 187, 163, 209], "category_id": 60, "category_name": "minimize"}, {"bbox": [346, 358, 356, 371], "category_id": 11, "category_name": "arrow_down"}, {"bbox": [1043, 351, 1055, 365], "category_id": 21, "category_name": "alarm"}, {"bbox": [996, 192, 1023, 219], "category_id": 39, "category_name": "gmail"}, {"bbox": [175, 259, 202, 286], "category_id": 59, "category_name": "megaphone"}, {"bbox": [783, 369, 832, 418], "category_id": 79, "category_name": "refresh"}, {"bbox": [735, 211, 754, 227], "category_id": 58, "category_name": "contrast"}, {"bbox": [834, 376, 854, 405], "category_id": 4, "category_name": "eye"}, {"bbox": [678, 289, 718, 300], "category_id": 69, "category_name": "google"}, {"bbox": [734, 17, 764, 57], "category_id": 98, "category_name": "user"}, {"bbox": [15, 384, 44, 413], "category_id": 71, "category_name": "qr_code"}, {"bbox": [238, 138, 258, 151], "category_id": 60, "category_name": "minimize"}, {"bbox": [816, 267, 826, 280], "category_id": 84, "category_name": "fab"}, {"bbox": [1017, 47, 1046, 76], "category_id": 97, "category_name": "video_camera"}, {"bbox": [407, 101, 438, 132], "category_id": 22, "category_name": "computer"}, {"bbox": [318, 165, 364, 211], "category_id": 99, "category_name": "trophy"}, {"bbox": [598, 236, 616, 250], "category_id": 65, "category_name": "facebook"}, {"bbox": [64, 1, 84, 23], "category_id": 30, "category_name": "sort"}, {"bbox": [145, 391, 168, 414], "category_id": 73, "category_name": "profile_avatar"}, {"bbox": [796, 60, 843, 107], "category_id": 86, "category_name": "folder"}, {"bbox": [944, 336, 994, 374], "category_id": 72, "category_name": "add"}, {"bbox": [317, 323, 349, 355], "category_id": 27, "category_name": "question"}, {"bbox": [172, 144, 202, 177], "category_id": 7, "category_name": "delete"}, {"bbox": [977, 252, 1027, 302], "category_id": 32, "category_name": "fast_forward"}, {"bbox": [469, 35, 500, 65], "category_id": 58, "category_name": "contrast"}, {"bbox": [695, 199, 728, 240], "category_id": 99, "category_name": "trophy"}, {"bbox": [653, 347, 669, 364], "category_id": 85, "category_name": "share"}, {"bbox": [553, 270, 564, 281], "category_id": 11, "category_name": "arrow_down"}, {"bbox": [170, 16, 211, 57], "category_id": 63, "category_name": "volume"}, {"bbox": [1116, 247, 1126, 257], "category_id": 23, "category_name": "edit"}, {"bbox": [348, 69, 387, 108], "category_id": 32, "category_name": "fast_forward"}, {"bbox": [10, 158, 29, 176], "category_id": 66, "category_name": "save"}, {"bbox": [599, 177, 610, 190], "category_id": 82, "category_name": "rewind"}, {"bbox": [412, 268, 423, 278], "category_id": 63, "category_name": "volume"}, {"bbox": [79, 298, 109, 328], "category_id": 11, "category_name": "arrow_down"}, {"bbox": [214, 65, 257, 97], "category_id": 24, "category_name": "printer"}, {"bbox": [740, 334, 762, 354], "category_id": 90, "category_name": "credit_card"}, {"bbox": [14, 107, 30, 123], "category_id": 102, "category_name": "globe"}, {"bbox": [290, 121, 331, 162], "category_id": 36, "category_name": "arrow_up"}, {"bbox": [29, 284, 44, 301], "category_id": 22, "category_name": "computer"}, {"bbox": [776, 279, 815, 318], "category_id": 45, "category_name": "thumbs_up"}, {"bbox": [684, 368, 716, 392], "category_id": 47, "category_name": "download"}, {"bbox": [398, 316, 426, 344], "category_id": 81, "category_name": "maximize"}, {"bbox": [222, 257, 232, 267], "category_id": 100, "category_name": "signal"}, {"bbox": [91, 98, 115, 148], "category_id": 24, "category_name": "printer"}, {"bbox": [1004, 8, 1032, 36], "category_id": 36, "category_name": "arrow_up"}, {"bbox": [674, 88, 713, 127], "category_id": 66, "category_name": "save"}, {"bbox": [245, 276, 259, 290], "category_id": 76, "category_name": "warning"}, {"bbox": [1153, 232, 1166, 245], "category_id": 12, "category_name": "trash"}]