[{"bbox": [155, 498, 166, 509], "category_id": 49, "category_name": "info"}, {"bbox": [248, 464, 271, 487], "category_id": 33, "category_name": "camera"}, {"bbox": [824, 439, 848, 458], "category_id": 28, "category_name": "airplane"}, {"bbox": [657, 89, 671, 101], "category_id": 24, "category_name": "printer"}, {"bbox": [820, 333, 855, 368], "category_id": 56, "category_name": "microphone"}, {"bbox": [738, 447, 748, 457], "category_id": 81, "category_name": "maximize"}, {"bbox": [939, 394, 982, 432], "category_id": 64, "category_name": "tag"}, {"bbox": [184, 333, 197, 346], "category_id": 89, "category_name": "cloud"}, {"bbox": [839, 204, 880, 245], "category_id": 100, "category_name": "signal"}, {"bbox": [525, 292, 551, 331], "category_id": 22, "category_name": "computer"}, {"bbox": [83, 16, 100, 33], "category_id": 9, "category_name": "send"}, {"bbox": [629, 13, 652, 36], "category_id": 34, "category_name": "barcode"}, {"bbox": [930, 235, 965, 254], "category_id": 86, "category_name": "folder"}, {"bbox": [459, 65, 475, 81], "category_id": 33, "category_name": "camera"}, {"bbox": [231, 93, 258, 120], "category_id": 26, "category_name": "fingerprint"}, {"bbox": [593, 62, 610, 79], "category_id": 32, "category_name": "fast_forward"}, {"bbox": [676, 89, 712, 125], "category_id": 16, "category_name": "music"}, {"bbox": [295, 232, 334, 271], "category_id": 50, "category_name": "mobile"}, {"bbox": [792, 405, 807, 417], "category_id": 46, "category_name": "battery"}, {"bbox": [113, 253, 125, 265], "category_id": 97, "category_name": "video_camera"}, {"bbox": [403, 338, 418, 354], "category_id": 26, "category_name": "fingerprint"}, {"bbox": [848, 13, 875, 37], "category_id": 62, "category_name": "arrow_left"}, {"bbox": [932, 89, 961, 118], "category_id": 17, "category_name": "bluetooth"}, {"bbox": [730, 375, 757, 402], "category_id": 102, "category_name": "globe"}, {"bbox": [309, 124, 351, 166], "category_id": 35, "category_name": "cart"}, {"bbox": [488, 381, 521, 414], "category_id": 39, "category_name": "gmail"}, {"bbox": [483, 363, 500, 379], "category_id": 91, "category_name": "external_link"}, {"bbox": [376, 407, 404, 435], "category_id": 18, "category_name": "grid"}, {"bbox": [323, 180, 347, 202], "category_id": 50, "category_name": "mobile"}, {"bbox": [528, 50, 553, 75], "category_id": 0, "category_name": "calculator"}, {"bbox": [726, 258, 776, 308], "category_id": 47, "category_name": "download"}, {"bbox": [518, 175, 562, 219], "category_id": 104, "category_name": "attach"}, {"bbox": [238, 341, 272, 375], "category_id": 94, "category_name": "reply"}, {"bbox": [80, 259, 102, 287], "category_id": 2, "category_name": "car"}, {"bbox": [234, 164, 252, 182], "category_id": 98, "category_name": "user"}, {"bbox": [125, 453, 145, 473], "category_id": 37, "category_name": "notifications"}, {"bbox": [21, 441, 31, 451], "category_id": 71, "category_name": "qr_code"}, {"bbox": [914, 160, 937, 184], "category_id": 52, "category_name": "crop"}, {"bbox": [123, 79, 143, 109], "category_id": 46, "category_name": "battery"}, {"bbox": [293, 440, 340, 487], "category_id": 22, "category_name": "computer"}, {"bbox": [633, 256, 655, 278], "category_id": 5, "category_name": "ticket"}, {"bbox": [241, 34, 256, 45], "category_id": 102, "category_name": "globe"}, {"bbox": [362, 316, 378, 341], "category_id": 23, "category_name": "edit"}, {"bbox": [899, 213, 919, 233], "category_id": 14, "category_name": "mail"}, {"bbox": [107, 438, 123, 454], "category_id": 25, "category_name": "dollar"}, {"bbox": [556, 442, 592, 478], "category_id": 2, "category_name": "car"}, {"bbox": [410, 261, 442, 293], "category_id": 79, "category_name": "refresh"}, {"bbox": [578, 240, 628, 290], "category_id": 97, "category_name": "video_camera"}, {"bbox": [778, 279, 791, 292], "category_id": 17, "category_name": "bluetooth"}, {"bbox": [554, 7, 584, 30], "category_id": 38, "category_name": "light_bulb"}, {"bbox": [491, 111, 509, 129], "category_id": 51, "category_name": "menu"}, {"bbox": [668, 246, 707, 263], "category_id": 69, "category_name": "google"}, {"bbox": [704, 213, 731, 243], "category_id": 31, "category_name": "pinterest"}, {"bbox": [254, 235, 268, 252], "category_id": 57, "category_name": "link"}, {"bbox": [588, 132, 632, 176], "category_id": 44, "category_name": "map"}, {"bbox": [921, 57, 939, 81], "category_id": 0, "category_name": "calculator"}, {"bbox": [141, 239, 188, 286], "category_id": 82, "category_name": "rewind"}, {"bbox": [782, 63, 794, 78], "category_id": 34, "category_name": "barcode"}, {"bbox": [794, 105, 812, 123], "category_id": 47, "category_name": "download"}, {"bbox": [14, 337, 59, 374], "category_id": 100, "category_name": "signal"}, {"bbox": [60, 338, 110, 381], "category_id": 44, "category_name": "map"}, {"bbox": [586, 29, 596, 39], "category_id": 41, "category_name": "check_mark"}, {"bbox": [653, 477, 671, 495], "category_id": 13, "category_name": "lock"}, {"bbox": [459, 242, 501, 284], "category_id": 97, "category_name": "video_camera"}, {"bbox": [325, 407, 358, 438], "category_id": 19, "category_name": "favorite"}, {"bbox": [564, 152, 585, 173], "category_id": 24, "category_name": "printer"}, {"bbox": [374, 120, 414, 169], "category_id": 97, "category_name": "video_camera"}, {"bbox": [409, 386, 437, 414], "category_id": 17, "category_name": "bluetooth"}, {"bbox": [604, 339, 643, 378], "category_id": 37, "category_name": "notifications"}, {"bbox": [791, 236, 808, 253], "category_id": 72, "category_name": "add"}, {"bbox": [33, 198, 73, 235], "category_id": 26, "category_name": "fingerprint"}, {"bbox": [439, 167, 486, 214], "category_id": 47, "category_name": "download"}, {"bbox": [34, 481, 84, 520], "category_id": 100, "category_name": "signal"}, {"bbox": [102, 158, 145, 205], "category_id": 99, "category_name": "trophy"}, {"bbox": [160, 108, 197, 146], "category_id": 97, "category_name": "video_camera"}, {"bbox": [796, 135, 818, 155], "category_id": 89, "category_name": "cloud"}, {"bbox": [435, 117, 479, 161], "category_id": 13, "category_name": "lock"}, {"bbox": [827, 147, 856, 190], "category_id": 9, "category_name": "send"}, {"bbox": [160, 25, 181, 46], "category_id": 63, "category_name": "volume"}, {"bbox": [861, 471, 894, 504], "category_id": 33, "category_name": "camera"}, {"bbox": [145, 65, 180, 107], "category_id": 96, "category_name": "call"}, {"bbox": [18, 27, 29, 38], "category_id": 102, "category_name": "globe"}, {"bbox": [941, 465, 983, 490], "category_id": 59, "category_name": "megaphone"}, {"bbox": [599, 422, 637, 460], "category_id": 15, "category_name": "laptop"}, {"bbox": [539, 260, 574, 290], "category_id": 30, "category_name": "sort"}, {"bbox": [778, 459, 817, 498], "category_id": 65, "category_name": "facebook"}, {"bbox": [924, 480, 939, 499], "category_id": 55, "category_name": "chart"}, {"bbox": [108, 110, 145, 147], "category_id": 10, "category_name": "mute"}, {"bbox": [587, 498, 613, 524], "category_id": 66, "category_name": "save"}, {"bbox": [413, 76, 424, 87], "category_id": 101, "category_name": "upload"}, {"bbox": [890, 434, 908, 450], "category_id": 101, "category_name": "upload"}, {"bbox": [166, 352, 209, 395], "category_id": 9, "category_name": "send"}, {"bbox": [742, 142, 753, 153], "category_id": 72, "category_name": "add"}, {"bbox": [662, 320, 700, 365], "category_id": 87, "category_name": "settings"}, {"bbox": [891, 270, 924, 309], "category_id": 9, "category_name": "send"}, {"bbox": [0, 33, 18, 64], "category_id": 55, "category_name": "chart"}, {"bbox": [604, 106, 614, 116], "category_id": 85, "category_name": "share"}, {"bbox": [145, 398, 169, 431], "category_id": 98, "category_name": "user"}, {"bbox": [662, 130, 694, 162], "category_id": 75, "category_name": "location"}, {"bbox": [669, 367, 679, 379], "category_id": 49, "category_name": "info"}, {"bbox": [331, 358, 359, 379], "category_id": 5, "category_name": "ticket"}, {"bbox": [210, 447, 233, 475], "category_id": 56, "category_name": "microphone"}, {"bbox": [356, 24, 405, 69], "category_id": 42, "category_name": "clock"}, {"bbox": [570, 350, 585, 363], "category_id": 28, "category_name": "airplane"}, {"bbox": [255, 162, 295, 212], "category_id": 89, "category_name": "cloud"}, {"bbox": [93, 482, 139, 521], "category_id": 8, "category_name": "home"}, {"bbox": [6, 124, 36, 164], "category_id": 11, "category_name": "arrow_down"}, {"bbox": [524, 393, 567, 436], "category_id": 11, "category_name": "arrow_down"}, {"bbox": [214, 407, 240, 420], "category_id": 57, "category_name": "link"}, {"bbox": [479, 88, 497, 106], "category_id": 34, "category_name": "barcode"}, {"bbox": [388, 211, 433, 256], "category_id": 8, "category_name": "home"}, {"bbox": [862, 150, 891, 179], "category_id": 68, "category_name": "file"}, {"bbox": [468, 502, 491, 520], "category_id": 73, "category_name": "profile_avatar"}, {"bbox": [705, 14, 753, 56], "category_id": 55, "category_name": "chart"}, {"bbox": [47, 287, 92, 332], "category_id": 13, "category_name": "lock"}, {"bbox": [687, 469, 735, 514], "category_id": 42, "category_name": "clock"}, {"bbox": [30, 2, 73, 47], "category_id": 43, "category_name": "bag"}, {"bbox": [937, 6, 957, 26], "category_id": 10, "category_name": "mute"}, {"bbox": [162, 159, 212, 209], "category_id": 16, "category_name": "music"}, {"bbox": [246, 122, 279, 155], "category_id": 58, "category_name": "contrast"}, {"bbox": [665, 37, 703, 79], "category_id": 41, "category_name": "check_mark"}, {"bbox": [271, 382, 318, 429], "category_id": 85, "category_name": "share"}, {"bbox": [356, 297, 367, 308], "category_id": 10, "category_name": "mute"}, {"bbox": [875, 25, 921, 60], "category_id": 92, "category_name": "moon"}, {"bbox": [951, 286, 975, 312], "category_id": 33, "category_name": "camera"}, {"bbox": [871, 138, 882, 148], "category_id": 75, "category_name": "location"}, {"bbox": [932, 350, 946, 364], "category_id": 94, "category_name": "reply"}, {"bbox": [457, 327, 489, 359], "category_id": 33, "category_name": "camera"}, {"bbox": [654, 294, 686, 319], "category_id": 15, "category_name": "laptop"}, {"bbox": [518, 464, 545, 514], "category_id": 76, "category_name": "warning"}, {"bbox": [601, 40, 620, 60], "category_id": 77, "category_name": "dashboard"}, {"bbox": [840, 82, 852, 97], "category_id": 75, "category_name": "location"}, {"bbox": [462, 424, 472, 434], "category_id": 90, "category_name": "credit_card"}, {"bbox": [621, 57, 631, 67], "category_id": 54, "category_name": "calendar"}, {"bbox": [511, 331, 556, 376], "category_id": 17, "category_name": "bluetooth"}, {"bbox": [469, 437, 511, 479], "category_id": 66, "category_name": "save"}, {"bbox": [809, 301, 838, 332], "category_id": 51, "category_name": "menu"}, {"bbox": [284, 48, 330, 94], "category_id": 11, "category_name": "arrow_down"}, {"bbox": [744, 207, 784, 253], "category_id": 32, "category_name": "fast_forward"}, {"bbox": [642, 431, 674, 473], "category_id": 89, "category_name": "cloud"}, {"bbox": [193, 475, 229, 525], "category_id": 15, "category_name": "laptop"}, {"bbox": [826, 5, 837, 15], "category_id": 43, "category_name": "bag"}, {"bbox": [38, 96, 72, 143], "category_id": 9, "category_name": "send"}, {"bbox": [382, 461, 429, 508], "category_id": 28, "category_name": "airplane"}, {"bbox": [558, 294, 595, 339], "category_id": 65, "category_name": "facebook"}, {"bbox": [504, 86, 527, 109], "category_id": 75, "category_name": "location"}, {"bbox": [305, 34, 319, 45], "category_id": 12, "category_name": "trash"}, {"bbox": [206, 321, 227, 342], "category_id": 44, "category_name": "map"}, {"bbox": [909, 189, 922, 203], "category_id": 35, "category_name": "cart"}, {"bbox": [121, 33, 156, 61], "category_id": 95, "category_name": "twitter"}, {"bbox": [611, 195, 655, 240], "category_id": 7, "category_name": "delete"}, {"bbox": [948, 56, 980, 86], "category_id": 19, "category_name": "favorite"}, {"bbox": [879, 315, 916, 340], "category_id": 53, "category_name": "flag"}, {"bbox": [637, 160, 647, 176], "category_id": 67, "category_name": "play"}, {"bbox": [757, 7, 800, 50], "category_id": 36, "category_name": "arrow_up"}, {"bbox": [414, 293, 437, 321], "category_id": 12, "category_name": "trash"}, {"bbox": [882, 354, 931, 403], "category_id": 62, "category_name": "arrow_left"}, {"bbox": [955, 28, 973, 44], "category_id": 25, "category_name": "dollar"}, {"bbox": [142, 310, 159, 327], "category_id": 22, "category_name": "computer"}, {"bbox": [680, 166, 718, 204], "category_id": 82, "category_name": "rewind"}, {"bbox": [41, 430, 85, 480], "category_id": 58, "category_name": "contrast"}, {"bbox": [679, 401, 728, 450], "category_id": 43, "category_name": "bag"}, {"bbox": [722, 100, 738, 116], "category_id": 25, "category_name": "dollar"}, {"bbox": [7, 292, 22, 307], "category_id": 30, "category_name": "sort"}, {"bbox": [235, 431, 270, 451], "category_id": 68, "category_name": "file"}, {"bbox": [96, 318, 115, 334], "category_id": 5, "category_name": "ticket"}, {"bbox": [180, 306, 203, 332], "category_id": 97, "category_name": "video_camera"}, {"bbox": [38, 47, 85, 94], "category_id": 95, "category_name": "twitter"}, {"bbox": [399, 364, 421, 386], "category_id": 72, "category_name": "add"}, {"bbox": [898, 508, 916, 526], "category_id": 32, "category_name": "fast_forward"}, {"bbox": [760, 348, 806, 398], "category_id": 4, "category_name": "eye"}, {"bbox": [100, 399, 128, 427], "category_id": 19, "category_name": "favorite"}, {"bbox": [718, 83, 730, 93], "category_id": 66, "category_name": "save"}, {"bbox": [952, 353, 969, 372], "category_id": 78, "category_name": "television"}, {"bbox": [121, 210, 149, 238], "category_id": 98, "category_name": "user"}, {"bbox": [13, 169, 53, 198], "category_id": 64, "category_name": "tag"}, {"bbox": [483, 33, 518, 73], "category_id": 41, "category_name": "check_mark"}, {"bbox": [700, 287, 713, 299], "category_id": 57, "category_name": "link"}, {"bbox": [750, 165, 788, 203], "category_id": 65, "category_name": "facebook"}, {"bbox": [348, 206, 380, 238], "category_id": 46, "category_name": "battery"}, {"bbox": [286, 99, 301, 114], "category_id": 5, "category_name": "ticket"}, {"bbox": [123, 68, 134, 79], "category_id": 76, "category_name": "warning"}, {"bbox": [542, 231, 569, 251], "category_id": 43, "category_name": "bag"}, {"bbox": [277, 489, 311, 517], "category_id": 4, "category_name": "eye"}, {"bbox": [192, 42, 240, 80], "category_id": 38, "category_name": "light_bulb"}, {"bbox": [643, 54, 662, 73], "category_id": 54, "category_name": "calendar"}, {"bbox": [443, 4, 472, 50], "category_id": 95, "category_name": "twitter"}, {"bbox": [132, 380, 146, 394], "category_id": 32, "category_name": "fast_forward"}, {"bbox": [190, 406, 213, 432], "category_id": 74, "category_name": "cut"}, {"bbox": [173, 290, 188, 304], "category_id": 20, "category_name": "headphones"}, {"bbox": [721, 351, 731, 362], "category_id": 103, "category_name": "arrow_right"}, {"bbox": [917, 85, 932, 100], "category_id": 67, "category_name": "play"}, {"bbox": [938, 163, 969, 194], "category_id": 31, "category_name": "pinterest"}, {"bbox": [613, 475, 638, 517], "category_id": 104, "category_name": "attach"}, {"bbox": [620, 404, 630, 416], "category_id": 56, "category_name": "microphone"}, {"bbox": [152, 174, 162, 186], "category_id": 43, "category_name": "bag"}, {"bbox": [5, 312, 15, 322], "category_id": 34, "category_name": "barcode"}, {"bbox": [527, 84, 560, 127], "category_id": 34, "category_name": "barcode"}, {"bbox": [191, 235, 239, 283], "category_id": 34, "category_name": "barcode"}, {"bbox": [315, 313, 357, 355], "category_id": 1, "category_name": "filter"}]